odoo/addons/l10n_es_aeat_sii_taxfree/README.rst
odoo/addons/l10n_es_aeat_sii_taxfree/__init__.py
odoo/addons/l10n_es_aeat_sii_taxfree/__manifest__.py
odoo/addons/l10n_es_aeat_sii_taxfree/i18n/es.po
odoo/addons/l10n_es_aeat_sii_taxfree/i18n/l10n_es_aeat_sii_taxfree.pot
odoo/addons/l10n_es_aeat_sii_taxfree/models/__init__.py
odoo/addons/l10n_es_aeat_sii_taxfree/models/account_fiscal_position.py
odoo/addons/l10n_es_aeat_sii_taxfree/models/account_move.py
odoo/addons/l10n_es_aeat_sii_taxfree/readme/CONFIGURE.rst
odoo/addons/l10n_es_aeat_sii_taxfree/readme/CONTRIBUTORS.rst
odoo/addons/l10n_es_aeat_sii_taxfree/readme/DESCRIPTION.rst
odoo/addons/l10n_es_aeat_sii_taxfree/readme/DEVELOP.rst
odoo/addons/l10n_es_aeat_sii_taxfree/readme/HISTORY.rst
odoo/addons/l10n_es_aeat_sii_taxfree/readme/INSTALL.rst
odoo/addons/l10n_es_aeat_sii_taxfree/readme/ROADMAP.rst
odoo/addons/l10n_es_aeat_sii_taxfree/readme/USAGE.rst
odoo/addons/l10n_es_aeat_sii_taxfree/static/description/SII_devolucion_IVA_viajeros.csv
odoo/addons/l10n_es_aeat_sii_taxfree/static/description/config_pos_fiscal.png
odoo/addons/l10n_es_aeat_sii_taxfree/static/description/icon.png
odoo/addons/l10n_es_aeat_sii_taxfree/static/description/index.html
odoo/addons/l10n_es_aeat_sii_taxfree/tests/__init__.py
odoo/addons/l10n_es_aeat_sii_taxfree/tests/test_l10n_es_aeat_sii_taxfree.py
odoo/addons/l10n_es_aeat_sii_taxfree/views/account_fiscal_position_views.xml
odoo_addon_l10n_es_aeat_sii_taxfree-16.0.2.0.2.dist-info/METADATA
odoo_addon_l10n_es_aeat_sii_taxfree-16.0.2.0.2.dist-info/WHEEL
odoo_addon_l10n_es_aeat_sii_taxfree-16.0.2.0.2.dist-info/top_level.txt
odoo_addon_l10n_es_aeat_sii_taxfree-16.0.2.0.2.dist-info/RECORD
